oneread/__init__.py
oneread/__main__.py
oneread/cli.py
oneread-1.0.0.dist-info/METADATA
oneread-1.0.0.dist-info/WHEEL
oneread-1.0.0.dist-info/entry_points.txt
oneread-1.0.0.dist-info/RECORD
