Metadata-Version: 2.4
Name: oneread
Version: 1.0.0
Summary: A terminal utility to display one daily article for 'positive news' and 'scientific interviews'
Project-URL: Homepage, https://github.com/decodingchris/OneRead
Project-URL: Bug Tracker, https://github.com/decodingchris/OneRead/issues
Author: Decoding Chris
License: MIT
Classifier: Environment :: Console
Classifier: Intended Audience :: End Users/Desktop
Classifier: License :: OSI Approved :: MIT License
Classifier: Operating System :: OS Independent
Classifier: Programming Language :: Python :: 3
Classifier: Topic :: Utilities
Requires-Python: >=3.10
Requires-Dist: click>=8.0.0
Requires-Dist: requests>=2.25.0
Requires-Dist: rich>=10.0.0
